google_music_proto/__about__.py
google_music_proto/__init__.py
google_music_proto/mobileclient/__init__.py
google_music_proto/mobileclient/calls.py
google_music_proto/mobileclient/constants.py
google_music_proto/mobileclient/models.py
google_music_proto/mobileclient/schemas.py
google_music_proto/mobileclient/types.py
google_music_proto/models.py
google_music_proto/musicmanager/__init__.py
google_music_proto/musicmanager/calls.py
google_music_proto/musicmanager/constants.py
google_music_proto/musicmanager/models.py
google_music_proto/musicmanager/pb/__init__.py
google_music_proto/musicmanager/pb/download_pb2.py
google_music_proto/musicmanager/pb/locker_pb2.py
google_music_proto/musicmanager/pb/uits_pb2.py
google_music_proto/musicmanager/pb/upload_pb2.py
google_music_proto/musicmanager/utils.py
google_music_proto/oauth.py
google_music_proto-2.10.0.dist-info/LICENSE
google_music_proto-2.10.0.dist-info/WHEEL
google_music_proto-2.10.0.dist-info/METADATA
google_music_proto-2.10.0.dist-info/RECORD
